Metadata-Version: 2.1
Name: PyPanel
Version: 1.1
Summary: PyPanel is a module used to create beautiful tools
Home-page: https://github.com/CSM-BlueRed/PyPanel
Author: BlueRed
License: UNKNOWN
Keywords: python,panel,tool,terminal,tui
Platform: UNKNOWN
Classifier: Programming Language :: Python :: 3
Classifier: License :: OSI Approved :: MIT License
Requires-Python: >=3.6
